safari_sdk/__init__.py
safari_sdk/agent/framework/agent_framework.py
safari_sdk/agent/framework/agents/agent.py
safari_sdk/agent/framework/agents/agent_test.py
safari_sdk/agent/framework/comms/external_controller.py
safari_sdk/agent/framework/comms/external_controller_test.py
safari_sdk/agent/framework/comms/passive_controller.py
safari_sdk/agent/framework/config.py
safari_sdk/agent/framework/config_test.py
safari_sdk/agent/framework/constants.py
safari_sdk/agent/framework/embodiments/aloha.py
safari_sdk/agent/framework/embodiments/aloha_fast_api_endpoints.py
safari_sdk/agent/framework/embodiments/aloha_test.py
safari_sdk/agent/framework/embodiments/embodiment.py
safari_sdk/agent/framework/embodiments/fast_api_endpoint.py
safari_sdk/agent/framework/embodiments/fr3_duo.py
safari_sdk/agent/framework/embodiments/fr3_duo_endpoints.py
safari_sdk/agent/framework/embodiments/fr3_duo_test.py
safari_sdk/agent/framework/embodiments/omega_star.py
safari_sdk/agent/framework/embodiments/omega_star_fast_api_endpoints.py
safari_sdk/agent/framework/embodiments/omega_star_test.py
safari_sdk/agent/framework/event_bus/audio_event_handler.py
safari_sdk/agent/framework/event_bus/audio_event_handler_test.py
safari_sdk/agent/framework/event_bus/event_bus.py
safari_sdk/agent/framework/event_bus/event_bus_test.py
safari_sdk/agent/framework/event_bus/event_stream_handler.py
safari_sdk/agent/framework/event_bus/event_stream_handler_test.py
safari_sdk/agent/framework/event_bus/tool_call_event_handler.py
safari_sdk/agent/framework/event_bus/tool_call_event_handler_test.py
safari_sdk/agent/framework/flags.py
safari_sdk/agent/framework/live_api/live_handler.py
safari_sdk/agent/framework/live_api/live_handler_test.py
safari_sdk/agent/framework/live_api/testdata/input_img.png
safari_sdk/agent/framework/tools/ensemble_success_detection.py
safari_sdk/agent/framework/tools/fast_api_tools.py
safari_sdk/agent/framework/tools/fast_api_tools_test.py
safari_sdk/agent/framework/tools/fulfill_order.py
safari_sdk-2.86.0.dist-info/METADATA
safari_sdk-2.86.0.dist-info/WHEEL
safari_sdk-2.86.0.dist-info/entry_points.txt
safari_sdk-2.86.0.dist-info/licenses/LICENSE
safari_sdk-2.86.0.dist-info/RECORD
